sqs_client/__init__.py
sqs_client/client.py
sqs_client/publisher.py
sqs_client/task.py
sqs_client-0.1.7.dist-info/LICENSE
sqs_client-0.1.7.dist-info/METADATA
sqs_client-0.1.7.dist-info/WHEEL
sqs_client-0.1.7.dist-info/top_level.txt
sqs_client-0.1.7.dist-info/RECORD
