Metadata-Version: 2.1
Name: sqs-client
Version: 0.1.7
Summary: SQS client
Author-email: Digital Fortress <hai.huynh@digitalfortress.dev>
Project-URL: Homepage, https://github.com/digitalfortress-dev/python-sqs-client
Project-URL: Issues, https://github.com/digitalfortress-dev/python-sqs-client/issues
Classifier: Programming Language :: Python :: 3
Classifier: License :: OSI Approved :: MIT License
Classifier: Operating System :: OS Independent
Requires-Python: >=3.8
License-File: LICENSE
